LICENSE.txt
setup.py
ahmed.egg-info/PKG-INFO
ahmed.egg-info/SOURCES.txt
ahmed.egg-info/dependency_links.txt
ahmed.egg-info/top_level.txt
code/__init__.py